{
  "products": [
    {
      "id": "1",
      "name": "Sakura Kinomoto",
      "size": 15,
      "price": 45000,
      "stock": 15,
      "url": "https://www.manga-news.com/public/images/goodies/card-captor-sakura-clear-card-arc-sakura-kinomoto-rocket-beat-souyokusha-1.jpg"
    },
    {
      "id": "2",
      "name": "Spider Gwen",
      "size": 30,
      "price": 85000,
      "stock": 24,
      "url": "https://i.pinimg.com/originals/00/d7/03/00d703671666de7df936c31971ee9036.jpg"
    },
    {
      "id": "3",
      "name": "Lady Sylvanas",
      "size": 15,
      "price": 50000,
      "stock": 8,
      "url": "https://i5.walmartimages.com/asr/fe6715bc-47f7-4f3a-be66-f76ea6e5eab0.45d1f416a45aae95f092dfbc512d60c4.jpeg?odnHeight=450&odnWidth=450&odnBg=ffffff"
    },
    {
      "id": "4",
      "name": "Bombom",
      "size": 10,
      "price": 25000,
      "stock": 33,
      "url": "https://img.smyk.com/https://bin.smyk.com/media/product/390/5/atomowki-bojka-breloczek-z-figurka-6098064.jpg"
    },
    {
      "id": "b2a2",
      "name": "Majin Vegueta",
      "size": "45",
      "price": "100000",
      "stock": "2",
      "url": "https://i.pinimg.com/originals/97/ff/6b/97ff6b3d37381dad9dc3eeb970621b11.jpg"
    },
    {
      "id": "7562",
      "name": "Buu",
      "size": "30",
      "price": "60000",
      "stock": "10",
      "url": "https://item-shopping.c.yimg.jp/i/n/izutonchan_ton05_2_d_20230507141513"
    },
    {
      "id": "7bf7",
      "name": "Gohan SSJ2 ",
      "size": "30",
      "price": "70000",
      "stock": "46",
      "url": "https://http2.mlstatic.com/action-figure-gohan-ssj2-dragon-ball-z-25cm-D_NQ_NP_892630-MLB26327928803_112017-F.jpg"
    },
    {
      "id": "80d8",
      "name": "Shogun Raiden",
      "size": "30",
      "price": "75000",
      "stock": "89",
      "url": "https://genshinstar.com/wp-content/uploads/2023/01/Raiden-Shogun-Musou-Shinsetsu-Action-Figure-01-990x990.jpg"
    }
  ]
}